odoo/addons/account_invoice_currency_taxes/README.rst
odoo/addons/account_invoice_currency_taxes/__init__.py
odoo/addons/account_invoice_currency_taxes/__manifest__.py
odoo/addons/account_invoice_currency_taxes/i18n/account_invoice_currency_taxes.pot
odoo/addons/account_invoice_currency_taxes/i18n/es.po
odoo/addons/account_invoice_currency_taxes/i18n/it.po
odoo/addons/account_invoice_currency_taxes/models/__init__.py
odoo/addons/account_invoice_currency_taxes/models/account_tax.py
odoo/addons/account_invoice_currency_taxes/readme/CONTRIBUTORS.rst
odoo/addons/account_invoice_currency_taxes/readme/DESCRIPTION.rst
odoo/addons/account_invoice_currency_taxes/readme/HISTORY.rst
odoo/addons/account_invoice_currency_taxes/readme/USAGE.rst
odoo/addons/account_invoice_currency_taxes/static/description/icon.png
odoo/addons/account_invoice_currency_taxes/static/description/index.html
odoo/addons/account_invoice_currency_taxes/static/description/out_invoice.jpg
odoo/addons/account_invoice_currency_taxes/tests/__init__.py
odoo/addons/account_invoice_currency_taxes/tests/test_account_tax.py
odoo/addons/account_invoice_currency_taxes/views/tax_groups_totals.xml
odoo_addon_account_invoice_currency_taxes-16.0.1.0.2.dist-info/METADATA
odoo_addon_account_invoice_currency_taxes-16.0.1.0.2.dist-info/WHEEL
odoo_addon_account_invoice_currency_taxes-16.0.1.0.2.dist-info/top_level.txt
odoo_addon_account_invoice_currency_taxes-16.0.1.0.2.dist-info/RECORD
